registrate/__init__.py
registrate/models.py
registrate/registers.py
registrate/utils.py
registrate-0.1.6.dist-info/LICENSE
registrate-0.1.6.dist-info/WHEEL
registrate-0.1.6.dist-info/METADATA
registrate-0.1.6.dist-info/RECORD
